gapstop/__init__.py
gapstop/bibtex.py
gapstop/constants.py
gapstop/objects.py
gapstop/protocols.conf
gapstop/protocols/__init__.py
gapstop/protocols/protocol_base.py
gapstop/protocols/protocol_extract_coordinates.py
gapstop/protocols/protocol_gapstop_tm.py
gapstop/tests/__init__.py
gapstop/tests/tests_gapstop_tm.py
scipion_em_gapstop-3.0.1.dist-info/LICENSE
scipion_em_gapstop-3.0.1.dist-info/METADATA
scipion_em_gapstop-3.0.1.dist-info/WHEEL
scipion_em_gapstop-3.0.1.dist-info/entry_points.txt
scipion_em_gapstop-3.0.1.dist-info/top_level.txt
scipion_em_gapstop-3.0.1.dist-info/RECORD
